CHANGELOG.md
LICENSE
MANIFEST.in
README.md
setup.cfg
setup.py
whois_similarity_distance/__init__.py
whois_similarity_distance/__version__.py
whois_similarity_distance/whois_distance.py
whois_similarity_distance/wsd_domains.py
whois_similarity_distance.egg-info/PKG-INFO
whois_similarity_distance.egg-info/SOURCES.txt
whois_similarity_distance.egg-info/dependency_links.txt
whois_similarity_distance.egg-info/entry_points.txt
whois_similarity_distance.egg-info/requires.txt
whois_similarity_distance.egg-info/top_level.txt
whois_similarity_distance/util/__init__.py
whois_similarity_distance/util/constants.py
whois_similarity_distance/util/gbc_cls.p
whois_similarity_distance/util/whois_obj.py