Metadata-Version: 1.1
Name: whois-similarity-distance
Version: 1.0.2
Summary:  This python scripts can calculate the WHOIS Similarity Distance between two given domains.
Home-page: https://github.com/stratosphereips/whois-similarity-distance
Author: Raúl B. Netto
Author-email: raulbeni@gmail.com
License: MIT
Download-URL: https://github.com/stratosphereips/whois-similarity-distance/archive/v1.0.2.tar.gz
Keywords: whois similarity
Platform: UNKNOWN
Classifier: Development Status :: 5 - Production/Stable
Classifier: Environment :: Console
Classifier: Intended Audience :: Information Technology
Classifier: Intended Audience :: System Administrators
Classifier: Intended Audience :: Telecommunications Industry
Classifier: License :: OSI Approved :: MIT License
Classifier: Programming Language :: Python
Classifier: Programming Language :: Python :: 2
Classifier: Programming Language :: Python :: 3
Classifier: Topic :: Security
